cufel_arena_agent/__init__.py
cufel_arena_agent/base.py
cufel_arena_agent/config.py
cufel_arena_agent/data_client.py
cufel_arena_agent/utils.py
cufel_arena_agent-1.0.1.dist-info/METADATA
cufel_arena_agent-1.0.1.dist-info/WHEEL
cufel_arena_agent-1.0.1.dist-info/top_level.txt
cufel_arena_agent-1.0.1.dist-info/RECORD
