Metadata-Version: 2.4
Name: cufel-arena-agent
Version: 1.0.1
Summary: CUFEL-Q Arena 平台智能体开发 SDK
Home-page: https://github.com/cufel-q/arena-agent-sdk
Author: CUFEL-Q Arena Team
Author-email: CUFEL-Q Arena Team <arena@cufel.edu.cn>
License: MIT
Project-URL: Homepage, https://arena.cufel.edu.cn
Project-URL: Documentation, https://arena.cufel.edu.cn/docs
Project-URL: Repository, https://github.com/cufel-q/arena-agent-sdk
Project-URL: Bug Tracker, https://github.com/cufel-q/arena-agent-sdk/issues
Keywords: quantitative-finance,trading,etf,portfolio,investment,arena,agent
Classifier: Development Status :: 4 - Beta
Classifier: Intended Audience :: Developers
Classifier: Intended Audience :: Financial and Insurance Industry
Classifier: License :: OSI Approved :: MIT License
Classifier: Operating System :: OS Independent
Classifier: Programming Language :: Python :: 3
Classifier: Programming Language :: Python :: 3.8
Classifier: Programming Language :: Python :: 3.9
Classifier: Programming Language :: Python :: 3.10
Classifier: Programming Language :: Python :: 3.11
Classifier: Programming Language :: Python :: 3.12
Classifier: Programming Language :: Python :: 3.13
Classifier: Topic :: Office/Business :: Financial :: Investment
Classifier: Topic :: Scientific/Engineering :: Artificial Intelligence
Requires-Python: >=3.8
Requires-Dist: pandas>=1.3.0
Requires-Dist: numpy>=1.20.0
Requires-Dist: quantchdb>=0.1.0
Provides-Extra: postgres
Requires-Dist: psycopg2-binary>=2.9.0; extra == "postgres"
Provides-Extra: dotenv
Requires-Dist: python-dotenv>=0.19.0; extra == "dotenv"
Provides-Extra: dev
Requires-Dist: pytest>=6.0.0; extra == "dev"
Requires-Dist: pytest-cov>=2.0.0; extra == "dev"
Requires-Dist: black>=21.0.0; extra == "dev"
Requires-Dist: flake8>=3.9.0; extra == "dev"
Provides-Extra: all
Requires-Dist: psycopg2-binary>=2.9.0; extra == "all"
Requires-Dist: python-dotenv>=0.19.0; extra == "all"
Dynamic: author
Dynamic: home-page
Dynamic: requires-python
